[{"model": "users.user", "pk": 1, "fields": {"password": "pbkdf2_sha256$600000$yGe1Fy6QBd4jSqIDpEoF4h$EhHEsNpLIAq5CCz73XzA0K+r0wmrw+4QXlQ6hHIfYak=", "last_login": "2024-05-21T07:26:47.063Z", "is_superuser": true, "first_name": "", "last_name": "", "is_staff": true, "is_active": true, "date_joined": "2024-05-21T07:16:05.897Z", "email": "admin@example.com", "phone": null, "city": null, "avatar": "", "groups": [], "user_permissions": []}}, {"model": "users.user", "pk": 2, "fields": {"password": "pbkdf2_sha256$600000$YPke2ZvUpMQuo1pF4VlUFt$GwGiJ+QCrwuuDHf71oOedQSF6YCnpMR6F3wbjXl4vd8=", "last_login": null, "is_superuser": false, "first_name": "", "last_name": "", "is_staff": false, "is_active": true, "date_joined": "2024-05-21T08:12:05.053Z", "email": "ivan@test.ru", "phone": null, "city": null, "avatar": "", "groups": [], "user_permissions": []}}, {"model": "users.user", "pk": 3, "fields": {"password": "pbkdf2_sha256$600000$QpxokOSoP0aBMQxnJuaQNL$rwexFXJERIacjYG7tHV8hPtK8oP36PrYJnWm1iwaTbo=", "last_login": null, "is_superuser": false, "first_name": "", "last_name": "", "is_staff": false, "is_active": true, "date_joined": "2024-05-21T08:12:25.164Z", "email": "stepan@test.ru", "phone": null, "city": null, "avatar": "", "groups": [], "user_permissions": []}}, {"model": "users.user", "pk": 4, "fields": {"password": "pbkdf2_sha256$600000$NX8Hszveid4mYhFGjU2ken$DfjURKq47vRWCoSX7gl7DmsjYllbMaQLH6tjcPNFjSE=", "last_login": null, "is_superuser": false, "first_name": "", "last_name": "", "is_staff": false, "is_active": true, "date_joined": "2024-05-21T08:13:04.749Z", "email": "vovan@test.ru", "phone": null, "city": null, "avatar": "", "groups": [], "user_permissions": []}}]